raincloud/__init__.py
raincloud/raincloud.py
RainCloud-0.1.0.post1.dist-info/METADATA
RainCloud-0.1.0.post1.dist-info/WHEEL
RainCloud-0.1.0.post1.dist-info/top_level.txt
RainCloud-0.1.0.post1.dist-info/RECORD
