Metadata-Version: 2.1
Name: RainCloud
Version: 0.1.0.post1
Summary: A package for creating raincloud plots
Home-page: https://github.com/Yosri-Ben-Halima/RaincloudPlot
Author: Yosri Ben Halima
Author-email: yosri.benhalima@ept.ucar.tn
Classifier: Programming Language :: Python :: 3
Classifier: License :: OSI Approved :: MIT License
Classifier: Operating System :: OS Independent
Requires-Python: >=3.6
Requires-Dist: matplotlib
Requires-Dist: seaborn
Requires-Dist: ptitprince
